LICENSE
MANIFEST.in
README.md
setup.cfg
setup.py
lz4_checkpoints/__init__.py
lz4_checkpoints/lz4meta.py
lz4_checkpoints/newline_reader.py
lz4_checkpoints.egg-info/PKG-INFO
lz4_checkpoints.egg-info/SOURCES.txt
lz4_checkpoints.egg-info/dependency_links.txt
lz4_checkpoints.egg-info/requires.txt
lz4_checkpoints.egg-info/top_level.txt