Metadata-Version: 1.1
Name: lz4-checkpoints
Version: 0.0.0
Summary: Builds LZ4 mapping file for random access
Home-page: https://github.com/ph4r05/lz4-checkpoints
Author: Dusan Klinec
Author-email: dusan.klinec@gmail.com
License: MIT
Platform: UNKNOWN
Classifier: Development Status :: 3 - Alpha
Classifier: Intended Audience :: Developers
Classifier: Programming Language :: Python
Classifier: Programming Language :: Python :: 2
Classifier: Programming Language :: Python :: 2.6
Classifier: Programming Language :: Python :: 2.7
Classifier: Programming Language :: Python :: 3
Classifier: Programming Language :: Python :: 3.3
Classifier: Programming Language :: Python :: 3.4
Classifier: Programming Language :: Python :: 3.5
Classifier: Topic :: Security
